Metadata-Version: 2.1
Name: ydr
Version: 0.0.1
Summary: Trading API
Home-page: https://github.com/yogeshtodarwal/ydr
Author: yogesh todarwal
Author-email: todarwa@kth.se
License: MIT license
Keywords: ydr
Platform: UNKNOWN
Classifier: Development Status :: 2 - Pre-Alpha
Classifier: Intended Audience :: Developers
Classifier: License :: OSI Approved :: MIT License
Classifier: Natural Language :: English
Classifier: Programming Language :: Python :: 3
Classifier: Programming Language :: Python :: 3.5
Classifier: Programming Language :: Python :: 3.6
Classifier: Programming Language :: Python :: 3.7
Classifier: Programming Language :: Python :: 3.8
Requires-Python: >=3.5
License-File: LICENSE
